fun_things/__init__.py
fun_things/ad_blocker_filter_parser/__init__.py
fun_things/ad_blocker_filter_parser/ad_blocker_filter_data.py
fun_things/ad_blocker_filter_parser/ad_blocker_filter_parser.py
fun_things/asynchronous.py
fun_things/boolean_query.py
fun_things/cache.py
fun_things/categorizer.py
fun_things/cli/__init__.py
fun_things/cli/freeze.py
fun_things/cli/install.py
fun_things/colored_formatter.py
fun_things/downloader.py
fun_things/environment.py
fun_things/fast_api/healthz.py
fun_things/frame.py
fun_things/generic.py
fun_things/generic_json_encoder.py
fun_things/key_wrapper.py
fun_things/language/__init__.py
fun_things/language/detect.py
fun_things/language/payload.py
fun_things/lazy.py
fun_things/logger.py
fun_things/math/__init__.py
fun_things/math/weighted_distribution.py
fun_things/middleware.py
fun_things/mongo_transaction/builder.py
fun_things/mongo_transaction/result.py
fun_things/mongo_transaction/transaction.py
fun_things/mutator/__init__.py
fun_things/mutator/affix.py
fun_things/mutator/mutate.py
fun_things/mutator/mutator.py
fun_things/mutator/payload.py
fun_things/mutator/postfix.py
fun_things/mutator/prefix.py
fun_things/network.py
fun_things/not_chalk.py
fun_things/opentelemetry/otlp_handler.py
fun_things/opentelemetry/otlp_helper.py
fun_things/parse.py
fun_things/proxy_uri.py
fun_things/pydantic/__init__.py
fun_things/pydantic/mongo_annotation.py
fun_things/pydantic/mongo_annotation_field.py
fun_things/pydantic/mongo_annotation_writer.py
fun_things/retry/async_retry.py
fun_things/retry/retry.py
fun_things/retry/retry_response.py
fun_things/singleton_factory/__init__.py
fun_things/singleton_factory/boto3_sf.py
fun_things/singleton_factory/elasticsearch_sf.py
fun_things/singleton_factory/mongo_sf.py
fun_things/singleton_factory/redis_sf.py
fun_things/singleton_hub/__init__.py
fun_things/singleton_hub/elasticsearch_hub.py
fun_things/singleton_hub/environment_hub.py
fun_things/singleton_hub/mongo_hub.py
fun_things/singleton_hub/redis_hub.py
fun_things-0.56.0.dist-info/METADATA
fun_things-0.56.0.dist-info/WHEEL
fun_things-0.56.0.dist-info/entry_points.txt
fun_things-0.56.0.dist-info/RECORD
